ewms_pilot/__init__.py
ewms_pilot/__main__.py
ewms_pilot/config.py
ewms_pilot/housekeeping.py
ewms_pilot/htchirp_tools.py
ewms_pilot/pilot.py
ewms_pilot/py.typed
ewms_pilot/init_container/__init__.py
ewms_pilot/init_container/init_container.py
ewms_pilot/tasks/__init__.py
ewms_pilot/tasks/io.py
ewms_pilot/tasks/map.py
ewms_pilot/tasks/task.py
ewms_pilot/tasks/wait_on_tasks.py
ewms_pilot/utils/__init__.py
ewms_pilot/utils/runner.py
ewms_pilot/utils/utils.py
ewms_pilot-1.0.5.dist-info/licenses/LICENSE
ewms_pilot-1.0.5.dist-info/METADATA
ewms_pilot-1.0.5.dist-info/WHEEL
ewms_pilot-1.0.5.dist-info/top_level.txt
ewms_pilot-1.0.5.dist-info/RECORD
