Metadata-Version: 2.4
Name: ewms-pilot
Version: 1.0.5
Summary: EWMS's Pilot: A Job Pilot for Processing EWMS Events/Tasks
Author-email: WIPAC Developers <developers@icecube.wisc.edu>
License: MIT License
Project-URL: Homepage, https://pypi.org/project/ewms-pilot/
Project-URL: Tracker, https://github.com/Observation-Management-Service/ewms-pilot/issues
Project-URL: Source, https://github.com/Observation-Management-Service/ewms-pilot
Keywords: pilot,Observation Management Service,Event Workflow Management Service,EWMS,message passing,MQ task
Classifier: Development Status :: 5 - Production/Stable
Classifier: Programming Language :: Python :: 3.12
Requires-Python: <3.13,>=3.12
License-File: LICENSE
Requires-Dist: htchirp
Requires-Dist: htcondor
Requires-Dist: oms-mqclient
Requires-Dist: numpy
Provides-Extra: pulsar
Requires-Dist: oms-mqclient[pulsar]; extra == "pulsar"
Provides-Extra: rabbitmq
Requires-Dist: oms-mqclient[rabbitmq]; extra == "rabbitmq"
Provides-Extra: nats
Requires-Dist: oms-mqclient[nats]; extra == "nats"
Provides-Extra: all
Requires-Dist: oms-mqclient[all]; extra == "all"
Provides-Extra: test
Requires-Dist: asyncstdlib; extra == "test"
Requires-Dist: pytest; extra == "test"
Requires-Dist: pytest-asyncio; extra == "test"
Requires-Dist: pytest-retry; extra == "test"
Provides-Extra: mypy
Requires-Dist: oms-mqclient[all]; extra == "mypy"
Requires-Dist: asyncstdlib; extra == "mypy"
Requires-Dist: pytest; extra == "mypy"
Requires-Dist: pytest-asyncio; extra == "mypy"
Requires-Dist: pytest-retry; extra == "mypy"
Dynamic: license-file
